NEOPRENE/__init__.py
NEOPRENE/NSRP/Analysis.py
NEOPRENE/NSRP/Calibration.py
NEOPRENE/NSRP/HiperParams.py
NEOPRENE/NSRP/MathematicalPropertiesNSRP.py
NEOPRENE/NSRP/PSOMdJ.py
NEOPRENE/NSRP/Simulation.py
NEOPRENE/NSRP/Statistics.py
NEOPRENE/NSRP/__init__.py
NEOPRENE/NSRP/inputs_simulation.py
NEOPRENE/NSRP/libs_NSRP.py
NEOPRENE/NSRP/outputs_simulation.py
NEOPRENE/NSRP/parameters_calibration.py
NEOPRENE/NSRP/utils.py
NEOPRENE/STNSRP/Analysis.py
NEOPRENE/STNSRP/Calibration.py
NEOPRENE/STNSRP/HiperParams.py
NEOPRENE/STNSRP/MathematicalPropertiesSTNSRP.py
NEOPRENE/STNSRP/PSOMdJ.py
NEOPRENE/STNSRP/Simulation.py
NEOPRENE/STNSRP/Statistics.py
NEOPRENE/STNSRP/__init__.py
NEOPRENE/STNSRP/inputs_simulation.py
NEOPRENE/STNSRP/libs_STNSRP.py
NEOPRENE/STNSRP/outputs_simulation.py
NEOPRENE/STNSRP/parameters_calibration.py
NEOPRENE/STNSRP/utils.py
notebooks/__init__.py
NEOPRENE-1.1.0.dist-info/LICENSE
NEOPRENE-1.1.0.dist-info/METADATA
NEOPRENE-1.1.0.dist-info/NOTICE
NEOPRENE-1.1.0.dist-info/WHEEL
NEOPRENE-1.1.0.dist-info/top_level.txt
NEOPRENE-1.1.0.dist-info/RECORD
