Metadata-Version: 2.1
Name: NEOPRENE
Version: 1.1.0
Summary: 🌎 Scripts and information to synthetic generation of precipitation based on Point Processes.
Home-page: https://github.com/IHCantabria/NEOPRENE
Author: Javier Diez-Sierra <javier.diez@unican.es>, Salvador Navas <salvador.navas@unican.es>, Manuel del Jesus <manuel.deljesus@unican.es>
Author-email: javier.diez@unican.es, salvador.navas@unican.es, manuel.deljesus@unican.es
Maintainer: Manuel del Jesus
Maintainer-email: manuel.deljesus@unican.es
License: GPLv3
Requires-Python: >=3.11, <4
License-File: LICENSE
License-File: NOTICE
Requires-Dist: numpy
Requires-Dist: pandas
Requires-Dist: scipy
Requires-Dist: datetime
Requires-Dist: matplotlib
Requires-Dist: pyyaml
Requires-Dist: haversine
Requires-Dist: tqdm
Requires-Dist: pyshp
Requires-Dist: shapely
Provides-Extra: plotting
Requires-Dist: matplotlib >=2.2.0 ; extra == 'plotting'
Requires-Dist: jupyter ; extra == 'plotting'
Requires-Dist: jupyterlab ; extra == 'plotting'
